odoo_mcp_server/__init__.py
odoo_mcp_server/server.py
drk_odoo_mcp_server-0.1.1.dist-info/METADATA
drk_odoo_mcp_server-0.1.1.dist-info/WHEEL
drk_odoo_mcp_server-0.1.1.dist-info/entry_points.txt
drk_odoo_mcp_server-0.1.1.dist-info/RECORD
